[{"id":"fa0cf80e-b8e9-46c2-a392-4b0972ef6cae","customer_id":"rrgtG3C1UHgIcBMMtfdSnF2Vxup2","vendor_id":"c1589737-0561-4d9d-a499-214655f16992","rider_id":null,"items":[{"qty": 1, "name": "Sambar Curry", "price": 25.0, "product_id": "fabb8dd4-d45e-4815-856a-ef12f02059b2"}],"total":51.25,"status":"CANCELLED","payment_method":"COD","payment_status":"PENDING","effective_address":"GMP3+3Q6,  P.MEANACHIPURAM","delivery_lat":9.534857,"delivery_lng":77.6504467,"resolved_pickup_lat":9.51,"resolved_pickup_lng":77.63,"pickup_otp":"1958","delivery_otp":"3054","created_at":"2026-02-26T21:13:55.294807+00:00","delivered_at":null,"completed_at":null,"cancelled_at":null,"eta_minutes":0,"vendor_name":"Royal Curry House","vendor_address":"Srivilliputhur","vendor_phone":"8897868951","vendor_image_url":null,"vendor_owner_id":"c1692237-7080-4da8-9411-ae970f5e1f20","rider_name":null,"rider_phone":null,"rider_avatar":null,"rider_live_lat":0,"rider_live_lng":0,"customer_name":"ganaparthi Manish ","customer_phone":"8897868951","status_display":"Cancelled","current_step":1}]